mo_awaoa-1.2.5.dist-info/licenses/LICENSE
moawaoa/__init__.py
moawaoa/algorithm.py
moawaoa/base.py
moawaoa/utils.py
mo_awaoa-1.2.5.dist-info/METADATA
mo_awaoa-1.2.5.dist-info/WHEEL
mo_awaoa-1.2.5.dist-info/top_level.txt
mo_awaoa-1.2.5.dist-info/RECORD
