Metadata-Version: 2.4
Name: mo-awaoa
Version: 1.2.5
Summary: Multi-Objective Adaptive Whale Optimization Algorithm (MO-AWAOA)
Home-page: https://github.com/safe049/mo-awaoa
Author: safe049
Author-email: safe049@163.com
Classifier: Programming Language :: Python :: 3
Classifier: License :: OSI Approved :: MIT License
Classifier: Operating System :: OS Independent
Requires-Python: >=3.7
License-File: LICENSE
Requires-Dist: numpy>=1.20
Requires-Dist: scipy>=1.7
Requires-Dist: matplotlib>=3.4
Requires-Dist: tqdm>=4.60
Dynamic: author
Dynamic: author-email
Dynamic: classifier
Dynamic: description
Dynamic: description-content-type
Dynamic: home-page
Dynamic: license-file
Dynamic: requires-dist
Dynamic: requires-python
Dynamic: summary
